pyoscar_emr/__init__.py
pyoscar_emr/appointment.py
pyoscar_emr/appointment_status.py
pyoscar_emr/demographic.py
pyoscar_emr/endpoints.py
pyoscar_emr/exceptions.py
pyoscar_emr/notes.py
pyoscar_emr/ontario_health_card.py
pyoscar_emr/oscar.py
pyoscar_emr/response_type.py
pyoscar_emr/util/get_oauth_creds.py
pyoscar_emr-0.9.12.dist-info/LICENSE
pyoscar_emr-0.9.12.dist-info/METADATA
pyoscar_emr-0.9.12.dist-info/WHEEL
pyoscar_emr-0.9.12.dist-info/RECORD
